pdpyras.py
pdpyras-5.4.0.dist-info/LICENSE
pdpyras-5.4.0.dist-info/METADATA
pdpyras-5.4.0.dist-info/WHEEL
pdpyras-5.4.0.dist-info/top_level.txt
pdpyras-5.4.0.dist-info/RECORD
